<?xml version="1.0" encoding="UTF-8"?>
<!DOCTYPE plist PUBLIC "-//Apple//DTD PLIST 1.0//EN" "http://www.apple.com/DTDs/PropertyList-1.0.dtd">
<plist version="1.0">
<array>
	<dict>
		<key>Actions</key>
		<array>
			<dict>
				<key>ActionColor</key>
				<string>Orange</string>
				<key>ActionUID</key>
				<integer>121</integer>
				<key>MacroActionType</key>
				<string>Comment</string>
				<key>StyledText</key>
				<data>
							cnRmZAAAAAADAAAAAgAA
							AAcAAABUWFQucnRmAQAA
							AC4gAgAAKwAAAAEAAAAY
							AgAAe1xydGYxXGFuc2lc
							YW5zaWNwZzEyNTJcY29j
							b2FydGYyNTgwClxjb2Nv
							YXRleHRzY2FsaW5nMFxj
							b2NvYXBsYXRmb3JtMHtc
							Zm9udHRibFxmMFxmbmls
							XGZjaGFyc2V0MCBSb2Jv
							dG8tUmVndWxhcjt9Cntc
							Y29sb3J0Ymw7XHJlZDI1
							NVxncmVlbjI1NVxibHVl
							MjU1O1xyZWQwXGdyZWVu
							MFxibHVlMDt9CntcKlxl
							eHBhbmRlZGNvbG9ydGJs
							OztcY3NzcmdiXGMwXGMw
							XGMwXGM4NDcwNlxjbmFt
							ZSBjb250cm9sVGV4dENv
							bG9yO30KXHBhcmRcdHg1
							NjBcdHgxMTIwXHR4MTY4
							MFx0eDIyNDBcdHgyODAw
							XHR4MzM2MFx0eDM5MjBc
							dHg0NDgwXHR4NTA0MFx0
							eDU2MDBcdHg2MTYwXHR4
							NjcyMFxwYXJkaXJuYXR1
							cmFsXHBhcnRpZ2h0ZW5m
							YWN0b3IwCgpcZjBcZnMy
							NiBcY2YyIDEuIEluIFN5
							c3RlbSBQcmVmZXJlbmNl
							cyAvIEFjY2Vzc2liaWxp
							dHkgLyBTaXJpXApDaGVj
							ayBib3ggZm9yIEVuYWJs
							ZSBUeXBlIHRvIFNpcmlc
							ClwKMi4gSW4gU3lzdGVt
							IFByZWZlcmVuY2VzIC8g
							U2lyaVwKU2V0IGtleWJv
							YXJkIHNob3J0Y3V0IHRv
							IG9wdGlvbi1zcGFjZX0B
							AAAAIwAAAAEAAAAHAAAA
							VFhULnJ0ZhAAAAABB5dg
							tgEAAAAAAAAAAAAA
							</data>
				<key>Title</key>
				<string>Requirements</string>
			</dict>
			<dict>
				<key>ActionUID</key>
				<integer>122</integer>
				<key>KeyCode</key>
				<integer>49</integer>
				<key>MacroActionType</key>
				<string>SimulateKeystroke</string>
				<key>Modifiers</key>
				<integer>256</integer>
				<key>ReleaseAll</key>
				<false/>
				<key>TargetApplication</key>
				<dict/>
				<key>TargetingType</key>
				<string>Front</string>
			</dict>
			<dict>
				<key>ActionUID</key>
				<integer>123</integer>
				<key>MacroActionType</key>
				<string>Pause</string>
				<key>Time</key>
				<string>.5</string>
				<key>TimeOutAbortsMacro</key>
				<true/>
			</dict>
			<dict>
				<key>Action</key>
				<string>ByTyping</string>
				<key>ActionUID</key>
				<integer>124</integer>
				<key>MacroActionType</key>
				<string>InsertText</string>
				<key>TargetApplication</key>
				<dict/>
				<key>TargetingType</key>
				<string>Front</string>
				<key>Text</key>
				<string>Siri</string>
			</dict>
			<dict>
				<key>ActionUID</key>
				<integer>125</integer>
				<key>KeyCode</key>
				<integer>36</integer>
				<key>MacroActionType</key>
				<string>SimulateKeystroke</string>
				<key>Modifiers</key>
				<integer>0</integer>
				<key>ReleaseAll</key>
				<false/>
				<key>TargetApplication</key>
				<dict/>
				<key>TargetingType</key>
				<string>Front</string>
			</dict>
			<dict>
				<key>ActionUID</key>
				<integer>126</integer>
				<key>MacroActionType</key>
				<string>Pause</string>
				<key>Time</key>
				<string>.5</string>
				<key>TimeOutAbortsMacro</key>
				<true/>
			</dict>
			<dict>
				<key>Action</key>
				<string>ByTyping</string>
				<key>ActionUID</key>
				<integer>127</integer>
				<key>MacroActionType</key>
				<string>InsertText</string>
				<key>TargetApplication</key>
				<dict/>
				<key>TargetingType</key>
				<string>Front</string>
				<key>Text</key>
				<string>It's Showtime</string>
			</dict>
			<dict>
				<key>ActionUID</key>
				<integer>128</integer>
				<key>KeyCode</key>
				<integer>36</integer>
				<key>MacroActionType</key>
				<string>SimulateKeystroke</string>
				<key>Modifiers</key>
				<integer>0</integer>
				<key>ReleaseAll</key>
				<false/>
				<key>TargetApplication</key>
				<dict/>
				<key>TargetingType</key>
				<string>Front</string>
			</dict>
		</array>
		<key>CreationDate</key>
		<real>642203803.54516995</real>
		<key>ModificationDate</key>
		<real>642203904.21309996</real>
		<key>Name</key>
		<string>showtime old way</string>
		<key>Triggers</key>
		<array/>
		<key>UID</key>
		<string>2088816C-8EF7-4DFC-98EF-A9F0153DB97F</string>
	</dict>
</array>
</plist>
