<?xml version="1.0" encoding="UTF-8"?>
<!DOCTYPE plist PUBLIC "-//Apple//DTD PLIST 1.0//EN" "http://www.apple.com/DTDs/PropertyList-1.0.dtd">
<plist version="1.0">
<array>
	<dict>
		<key>Actions</key>
		<array>
			<dict>
				<key>ActionColor</key>
				<string>Purple</string>
				<key>ActionUID</key>
				<integer>284</integer>
				<key>MacroActionType</key>
				<string>Comment</string>
				<key>StyledText</key>
				<data>
							cnRmZAAAAAADAAAAAgAA
							AAcAAABUWFQucnRmAQAA
							AC5QAwAAKwAAAAEAAABI
							AwAAe1xydGYxXGFuc2lc
							YW5zaWNwZzEyNTJcY29j
							b2FydGYyNTgwClxjb2Nv
							YXRleHRzY2FsaW5nMFxj
							b2NvYXBsYXRmb3JtMHtc
							Zm9udHRibFxmMFxmbmls
							XGZjaGFyc2V0MCBSb2Jv
							dG8tUmVndWxhcjt9Cntc
							Y29sb3J0Ymw7XHJlZDI1
							NVxncmVlbjI1NVxibHVl
							MjU1O1xyZWQwXGdyZWVu
							MFxibHVlMDt9CntcKlxl
							eHBhbmRlZGNvbG9ydGJs
							OztcY3NzcmdiXGMwXGMw
							XGMwXGM4NDcwNlxjbmFt
							ZSBjb250cm9sVGV4dENv
							bG9yO30KXHBhcmRcdHg1
							NjBcdHgxMTIwXHR4MTY4
							MFx0eDIyNDBcdHgyODAw
							XHR4MzM2MFx0eDM5MjBc
							dHg0NDgwXHR4NTA0MFx0
							eDU2MDBcdHg2MTYwXHR4
							NjcyMFxwYXJkaXJuYXR1
							cmFsXHBhcnRpZ2h0ZW5m
							YWN0b3IwCgpcZjBcZnMy
							NiBcY2YyICogU2V0cyBj
							dXJyZW50IHBsYXloZWFk
							IHBvc2l0aW9uIGFzIHRo
							ZSBvdXQgcG9pbnRcCiog
							TW92ZXMgcGxheWhlYWQg
							dG8gdGhlIGJlZ2lubmlu
							ZyBvZiB0aGUgY2xpcFwK
							KiBTZXRzIHRoYXQgYXMg
							dGhlIGluIHBvaW50XAoq
							IERlbGV0ZXMgdGhlIG5v
							dyBzZWxlY3RlZCByZWdp
							b25cCiogTW92ZXMgYmFj
							ayB0d28gc2Vjb25kc1wK
							KiBQbGF5cyB0aGUgdmlk
							ZW8vYXVkaW9cClwKVGhl
							IGFjdGlvbiB0byBmaW5k
							IHRoZSBiZWdpbm5pbmcg
							b2YgdGhlIGNsaXAgZmlu
							ZHMgYXVkaW8gb3Igdmlk
							ZW8gY2xpcCB3aXRoIHRo
							ZSBsZWFzdCB0aW1lIHRv
							IHRoZSBsZWZ0LiBFLmcu
							IGlmIHRoZXJlXCc5MnMg
							bW9yZSBhdWRpbyB0byB0
							aGUgbGVmdCB0aGFuIHZp
							ZGVvLCBpdCB3aWxsIGN1
							dCB0aGUgdmlkZW8sIGFu
							ZCB2aWNlIHZlcnNhLiBT
							ZWxlY3Rpb24gb2YgdHJh
							Y2tzIGRvZXMgbnRvIGFm
							ZmVjdCB0aGUgYmVoYXZp
							b3J9AQAAACMAAAABAAAA
							BwAAAFRYVC5ydGYQAAAA
							3MnUYLYBAAAAAAAAAAAA
							AA==
							</data>
				<key>Title</key>
				<string>Trim from the beginning of a clip to the current playhead position</string>
			</dict>
			<dict>
				<key>ActionColor</key>
				<string>Orange</string>
				<key>ActionUID</key>
				<integer>285</integer>
				<key>IsDisclosed</key>
				<false/>
				<key>MacroActionType</key>
				<string>Comment</string>
				<key>StyledText</key>
				<data>
							cnRmZAAAAAADAAAAAgAA
							AAcAAABUWFQucnRmAQAA
							AC6GAAAAKwAAAAEAAAB+
							AAAAe1xydGYxXGFuc2lc
							YW5zaWNwZzEyNTJcY29j
							b2FydGYxNTA0XGNvY29h
							c3VicnRmODMwCntcZm9u
							dHRibH0Ke1xjb2xvcnRi
							bDtccmVkMjU1XGdyZWVu
							MjU1XGJsdWUyNTU7fQp7
							XCpcZXhwYW5kZWRjb2xv
							cnRibDs7fQp9AQAAACMA
							AAABAAAABwAAAFRYVC5y
							dGYQAAAAlmygWbYBAAAA
							AAAAAAAAAA==
							</data>
				<key>Title</key>
				<string>Mark playhead position as the out point</string>
			</dict>
			<dict>
				<key>ActionUID</key>
				<integer>286</integer>
				<key>KeyCode</key>
				<integer>31</integer>
				<key>MacroActionType</key>
				<string>SimulateKeystroke</string>
				<key>Modifiers</key>
				<integer>0</integer>
				<key>ReleaseAll</key>
				<false/>
				<key>TargetApplication</key>
				<dict/>
				<key>TargetingType</key>
				<string>Front</string>
			</dict>
			<dict>
				<key>ActionColor</key>
				<string>Orange</string>
				<key>ActionUID</key>
				<integer>287</integer>
				<key>IsDisclosed</key>
				<false/>
				<key>MacroActionType</key>
				<string>Comment</string>
				<key>StyledText</key>
				<data>
							cnRmZAAAAAADAAAAAgAA
							AAcAAABUWFQucnRmAQAA
							AC6GAAAAKwAAAAEAAAB+
							AAAAe1xydGYxXGFuc2lc
							YW5zaWNwZzEyNTJcY29j
							b2FydGYxNTA0XGNvY29h
							c3VicnRmODMwCntcZm9u
							dHRibH0Ke1xjb2xvcnRi
							bDtccmVkMjU1XGdyZWVu
							MjU1XGJsdWUyNTU7fQp7
							XCpcZXhwYW5kZWRjb2xv
							cnRibDs7fQp9AQAAACMA
							AAABAAAABwAAAFRYVC5y
							dGYQAAAAlmygWbYBAAAA
							AAAAAAAAAA==
							</data>
				<key>Title</key>
				<string>Move playhead to the beginning of the clip</string>
			</dict>
			<dict>
				<key>ActionUID</key>
				<integer>288</integer>
				<key>KeyCode</key>
				<integer>41</integer>
				<key>MacroActionType</key>
				<string>SimulateKeystroke</string>
				<key>Modifiers</key>
				<integer>0</integer>
				<key>ReleaseAll</key>
				<false/>
				<key>TargetApplication</key>
				<dict/>
				<key>TargetingType</key>
				<string>Front</string>
			</dict>
			<dict>
				<key>ActionColor</key>
				<string>Orange</string>
				<key>ActionUID</key>
				<integer>289</integer>
				<key>IsDisclosed</key>
				<false/>
				<key>MacroActionType</key>
				<string>Comment</string>
				<key>StyledText</key>
				<data>
							cnRmZAAAAAADAAAAAgAA
							AAcAAABUWFQucnRmAQAA
							AC6GAAAAKwAAAAEAAAB+
							AAAAe1xydGYxXGFuc2lc
							YW5zaWNwZzEyNTJcY29j
							b2FydGYxNTA0XGNvY29h
							c3VicnRmODMwCntcZm9u
							dHRibH0Ke1xjb2xvcnRi
							bDtccmVkMjU1XGdyZWVu
							MjU1XGJsdWUyNTU7fQp7
							XCpcZXhwYW5kZWRjb2xv
							cnRibDs7fQp9AQAAACMA
							AAABAAAABwAAAFRYVC5y
							dGYQAAAAlmygWbYBAAAA
							AAAAAAAAAA==
							</data>
				<key>Title</key>
				<string>Mark playhead position as the in point</string>
			</dict>
			<dict>
				<key>ActionUID</key>
				<integer>290</integer>
				<key>KeyCode</key>
				<integer>34</integer>
				<key>MacroActionType</key>
				<string>SimulateKeystroke</string>
				<key>Modifiers</key>
				<integer>0</integer>
				<key>ReleaseAll</key>
				<false/>
				<key>TargetApplication</key>
				<dict/>
				<key>TargetingType</key>
				<string>Front</string>
			</dict>
			<dict>
				<key>ActionColor</key>
				<string>Orange</string>
				<key>ActionUID</key>
				<integer>291</integer>
				<key>IsDisclosed</key>
				<false/>
				<key>MacroActionType</key>
				<string>Comment</string>
				<key>StyledText</key>
				<data>
							cnRmZAAAAAADAAAAAgAA
							AAcAAABUWFQucnRmAQAA
							AC6GAAAAKwAAAAEAAAB+
							AAAAe1xydGYxXGFuc2lc
							YW5zaWNwZzEyNTJcY29j
							b2FydGYxNTA0XGNvY29h
							c3VicnRmODMwCntcZm9u
							dHRibH0Ke1xjb2xvcnRi
							bDtccmVkMjU1XGdyZWVu
							MjU1XGJsdWUyNTU7fQp7
							XCpcZXhwYW5kZWRjb2xv
							cnRibDs7fQp9AQAAACMA
							AAABAAAABwAAAFRYVC5y
							dGYQAAAAlmygWbYBAAAA
							AAAAAAAAAA==
							</data>
				<key>Title</key>
				<string>Delete now-selected region</string>
			</dict>
			<dict>
				<key>ActionUID</key>
				<integer>292</integer>
				<key>KeyCode</key>
				<integer>51</integer>
				<key>MacroActionType</key>
				<string>SimulateKeystroke</string>
				<key>Modifiers</key>
				<integer>256</integer>
				<key>ReleaseAll</key>
				<false/>
				<key>TargetApplication</key>
				<dict/>
				<key>TargetingType</key>
				<string>Front</string>
			</dict>
			<dict>
				<key>ActionColor</key>
				<string>Orange</string>
				<key>ActionUID</key>
				<integer>293</integer>
				<key>IsDisclosed</key>
				<false/>
				<key>MacroActionType</key>
				<string>Comment</string>
				<key>StyledText</key>
				<data>
							cnRmZAAAAAADAAAAAgAA
							AAcAAABUWFQucnRmAQAA
							AC6GAAAAKwAAAAEAAAB+
							AAAAe1xydGYxXGFuc2lc
							YW5zaWNwZzEyNTJcY29j
							b2FydGYxNTA0XGNvY29h
							c3VicnRmODMwCntcZm9u
							dHRibH0Ke1xjb2xvcnRi
							bDtccmVkMjU1XGdyZWVu
							MjU1XGJsdWUyNTU7fQp7
							XCpcZXhwYW5kZWRjb2xv
							cnRibDs7fQp9AQAAACMA
							AAABAAAABwAAAFRYVC5y
							dGYQAAAAlmygWbYBAAAA
							AAAAAAAAAA==
							</data>
				<key>Title</key>
				<string>Back up two seconds (one second per simulated keystroke)</string>
			</dict>
			<dict>
				<key>ActionUID</key>
				<integer>294</integer>
				<key>KeyCode</key>
				<integer>123</integer>
				<key>MacroActionType</key>
				<string>SimulateKeystroke</string>
				<key>Modifiers</key>
				<integer>197120</integer>
				<key>ReleaseAll</key>
				<false/>
				<key>TargetApplication</key>
				<dict/>
				<key>TargetingType</key>
				<string>Front</string>
			</dict>
			<dict>
				<key>ActionUID</key>
				<integer>295</integer>
				<key>KeyCode</key>
				<integer>123</integer>
				<key>MacroActionType</key>
				<string>SimulateKeystroke</string>
				<key>Modifiers</key>
				<integer>197120</integer>
				<key>ReleaseAll</key>
				<false/>
				<key>TargetApplication</key>
				<dict/>
				<key>TargetingType</key>
				<string>Front</string>
			</dict>
			<dict>
				<key>ActionColor</key>
				<string>Orange</string>
				<key>ActionUID</key>
				<integer>296</integer>
				<key>IsDisclosed</key>
				<false/>
				<key>MacroActionType</key>
				<string>Comment</string>
				<key>StyledText</key>
				<data>
							cnRmZAAAAAADAAAAAgAA
							AAcAAABUWFQucnRmAQAA
							AC6GAAAAKwAAAAEAAAB+
							AAAAe1xydGYxXGFuc2lc
							YW5zaWNwZzEyNTJcY29j
							b2FydGYxNTA0XGNvY29h
							c3VicnRmODMwCntcZm9u
							dHRibH0Ke1xjb2xvcnRi
							bDtccmVkMjU1XGdyZWVu
							MjU1XGJsdWUyNTU7fQp7
							XCpcZXhwYW5kZWRjb2xv
							cnRibDs7fQp9AQAAACMA
							AAABAAAABwAAAFRYVC5y
							dGYQAAAAlmygWbYBAAAA
							AAAAAAAAAA==
							</data>
				<key>Title</key>
				<string>Play audio/video</string>
			</dict>
			<dict>
				<key>ActionUID</key>
				<integer>297</integer>
				<key>KeyCode</key>
				<integer>49</integer>
				<key>MacroActionType</key>
				<string>SimulateKeystroke</string>
				<key>Modifiers</key>
				<integer>0</integer>
				<key>ReleaseAll</key>
				<false/>
				<key>TargetApplication</key>
				<dict/>
				<key>TargetingType</key>
				<string>Front</string>
			</dict>
		</array>
		<key>CreationDate</key>
		<real>507741448.505198</real>
		<key>ModificationDate</key>
		<real>646250843.08938396</real>
		<key>Name</key>
		<string>Trim Beginning</string>
		<key>Triggers</key>
		<array>
			<dict>
				<key>FireType</key>
				<string>Pressed</string>
				<key>KeyCode</key>
				<integer>11</integer>
				<key>MacroTriggerType</key>
				<string>HotKey</string>
				<key>Modifiers</key>
				<integer>2304</integer>
			</dict>
		</array>
		<key>UID</key>
		<string>38FB3388-67EA-4C53-AAE4-B2D005A7DC18</string>
	</dict>
</array>
</plist>
