<?xml version="1.0" encoding="UTF-8"?>
<!DOCTYPE plist PUBLIC "-//Apple//DTD PLIST 1.0//EN" "http://www.apple.com/DTDs/PropertyList-1.0.dtd">
<plist version="1.0">
<array>
	<dict>
		<key>Actions</key>
		<array>
			<dict>
				<key>ActionColor</key>
				<string>Red</string>
				<key>ActionUID</key>
				<integer>3935</integer>
				<key>IsDisclosed</key>
				<false/>
				<key>MacroActionType</key>
				<string>Comment</string>
				<key>StyledText</key>
				<data>
							cnRmZAAAAAADAAAAAgAA
							AAcAAABUWFQucnRmAQAA
							AC6GAAAAKwAAAAEAAAB+
							AAAAe1xydGYxXGFuc2lc
							YW5zaWNwZzEyNTJcY29j
							b2FydGYxNTA0XGNvY29h
							c3VicnRmODMwCntcZm9u
							dHRibH0Ke1xjb2xvcnRi
							bDtccmVkMjU1XGdyZWVu
							MjU1XGJsdWUyNTU7fQp7
							XCpcZXhwYW5kZWRjb2xv
							cnRibDs7fQp9AQAAACMA
							AAABAAAABwAAAFRYVC5y
							dGYQAAAAlmygWbYBAAAA
							AAAAAAAAAA==
							</data>
				<key>Title</key>
				<string>Hindenburg Shortcut DEPENDS on this!</string>
			</dict>
			<dict>
				<key>ActionUID</key>
				<integer>3509</integer>
				<key>MacroActionType</key>
				<string>Comment</string>
				<key>StyledText</key>
				<data>
							cnRmZAAAAAADAAAAAgAA
							AAcAAABUWFQucnRmAQAA
							AC5bAgAAKwAAAAEAAABT
							AgAAe1xydGYxXGFuc2lc
							YW5zaWNwZzEyNTJcY29j
							b2FydGYyNTEzClxjb2Nv
							YXRleHRzY2FsaW5nMFxj
							b2NvYXBsYXRmb3JtMHtc
							Zm9udHRibFxmMFxmc3dp
							c3NcZmNoYXJzZXQwIEhl
							bHZldGljYTt9CntcY29s
							b3J0Ymw7XHJlZDI1NVxn
							cmVlbjI1NVxibHVlMjU1
							O1xyZWQwXGdyZWVuMFxi
							bHVlMDt9CntcKlxleHBh
							bmRlZGNvbG9ydGJsOztc
							Y3NzcmdiXGMwXGMwXGMw
							XGM4NDcwNlxjbmFtZSBj
							b250cm9sVGV4dENvbG9y
							O30KXHBhcmRcdHg1NjBc
							dHgxMTIwXHR4MTY4MFx0
							eDIyNDBcdHgyODAwXHR4
							MzM2MFx0eDM5MjBcdHg0
							NDgwXHR4NTA0MFx0eDU2
							MDBcdHg2MTYwXHR4Njcy
							MFxwYXJkaXJuYXR1cmFs
							XHBhcnRpZ2h0ZW5mYWN0
							b3IwCgpcZjBcZnMyNiBc
							Y2YyIEFzc3VtaW5nIHRo
							YXQgdGhlIHRyaWdnZXIg
							dmFsdWUgZm9yIHRoaXMg
							bWFjcm8gaXMgYSBKU09O
							IG9iamVjdCBjb250YWlu
							aW5nIHRoZSBub3RpZmlj
							YXRpb24gcGFyYW1lcnRl
							cnMsXApjcmVhdGUgbG9j
							YWwgdmFyaWFibGVzIGZv
							ciB0aGVtLCBUaGUgc3Vw
							cG9ydGVkIGtleXMgZm9y
							IHRoaXMgSlNPTiBhcmU6
							IHR5cGUsIHRpdGxlLCBz
							dWJ0aXRsZSwgbWVzc2Fn
							ZSwgYW5kIHNvdW5kfQEA
							AAAjAAAAAQAAAAcAAABU
							WFQucnRmEAAAAG14d1+2
							AQAAAAAAAAAAAAA=
							</data>
				<key>Title</key>
				<string>Create local variables</string>
			</dict>
			<dict>
				<key>ActionUID</key>
				<integer>3510</integer>
				<key>MacroActionType</key>
				<string>SetVariablesToJSON</string>
				<key>Prefix</key>
				<string>Local_Alert_</string>
				<key>Text</key>
				<string>%TriggerValue%</string>
			</dict>
			<dict>
				<key>ActionUID</key>
				<integer>3511</integer>
				<key>MacroActionType</key>
				<string>Comment</string>
				<key>StyledText</key>
				<data>
							cnRmZAAAAAADAAAAAgAA
							AAcAAABUWFQucnRmAQAA
							AC7tAQAAKwAAAAEAAADl
							AQAAe1xydGYxXGFuc2lc
							YW5zaWNwZzEyNTJcY29j
							b2FydGYyNTEzClxjb2Nv
							YXRleHRzY2FsaW5nMFxj
							b2NvYXBsYXRmb3JtMHtc
							Zm9udHRibFxmMFxmc3dp
							c3NcZmNoYXJzZXQwIEhl
							bHZldGljYTt9CntcY29s
							b3J0Ymw7XHJlZDI1NVxn
							cmVlbjI1NVxibHVlMjU1
							O1xyZWQwXGdyZWVuMFxi
							bHVlMDt9CntcKlxleHBh
							bmRlZGNvbG9ydGJsOztc
							Y3NzcmdiXGMwXGMwXGMw
							XGM4NDcwNlxjbmFtZSBj
							b250cm9sVGV4dENvbG9y
							O30KXHBhcmRcdHg1NjBc
							dHgxMTIwXHR4MTY4MFx0
							eDIyNDBcdHgyODAwXHR4
							MzM2MFx0eDM5MjBcdHg0
							NDgwXHR4NTA0MFx0eDU2
							MDBcdHg2MTYwXHR4Njcy
							MFxwYXJkaXJuYXR1cmFs
							XHBhcnRpZ2h0ZW5mYWN0
							b3IwCgpcZjBcZnMyNiBc
							Y2YyIEZvciB0aGUgXCc5
							MXN1cHBvcnRlZFwnOTIg
							YXJndW1lbnRzIHRoYXQg
							bWF5IGhhdmUgYmVlbiBj
							cmVhdGVkLCBlbnN1cmUg
							bG93ZXIgY2FzZSBmb3Ig
							cHJvY2Vzc2luZyBjb25z
							aXN0ZW5jeX0BAAAAIwAA
							AAEAAAAHAAAAVFhULnJ0
							ZhAAAADZ2HdftgEAAAAA
							AAAAAAAA
							</data>
				<key>Title</key>
				<string>Prep arguments</string>
			</dict>
			<dict>
				<key>ActionUID</key>
				<integer>3512</integer>
				<key>Actions</key>
				<array>
					<dict>
						<key>ActionUID</key>
						<integer>3513</integer>
						<key>Conditions</key>
						<dict>
							<key>ConditionList</key>
							<array>
								<dict>
									<key>ConditionType</key>
									<string>Variable</string>
									<key>Variable</key>
									<string>Local_Alert_type</string>
									<key>VariableConditionType</key>
									<string>IsNotEmpty</string>
									<key>VariableValue</key>
									<string>value</string>
								</dict>
							</array>
							<key>ConditionListMatch</key>
							<string>All</string>
						</dict>
						<key>ElseActionListDisclosed</key>
						<false/>
						<key>ElseActions</key>
						<array/>
						<key>MacroActionType</key>
						<string>IfThenElse</string>
						<key>ThenActions</key>
						<array>
							<dict>
								<key>ActionUID</key>
								<integer>3514</integer>
								<key>MacroActionType</key>
								<string>SetVariableToText</string>
								<key>Text</key>
								<string>\L%Local_Alert_type%\E</string>
								<key>Variable</key>
								<string>Local_Alert_type</string>
							</dict>
						</array>
						<key>TimeOutAbortsMacro</key>
						<true/>
					</dict>
					<dict>
						<key>ActionUID</key>
						<integer>3515</integer>
						<key>Conditions</key>
						<dict>
							<key>ConditionList</key>
							<array>
								<dict>
									<key>ConditionType</key>
									<string>Variable</string>
									<key>Variable</key>
									<string>Local_Alert_title</string>
									<key>VariableConditionType</key>
									<string>IsNotEmpty</string>
									<key>VariableValue</key>
									<string>value</string>
								</dict>
							</array>
							<key>ConditionListMatch</key>
							<string>All</string>
						</dict>
						<key>ElseActionListDisclosed</key>
						<false/>
						<key>ElseActions</key>
						<array/>
						<key>MacroActionType</key>
						<string>IfThenElse</string>
						<key>ThenActions</key>
						<array>
							<dict>
								<key>ActionUID</key>
								<integer>3516</integer>
								<key>MacroActionType</key>
								<string>SetVariableToText</string>
								<key>Text</key>
								<string>\L%Local_Alert_title%\E</string>
								<key>Variable</key>
								<string>Local_Alert_title</string>
							</dict>
						</array>
						<key>TimeOutAbortsMacro</key>
						<true/>
					</dict>
					<dict>
						<key>ActionUID</key>
						<integer>3517</integer>
						<key>Conditions</key>
						<dict>
							<key>ConditionList</key>
							<array>
								<dict>
									<key>ConditionType</key>
									<string>Variable</string>
									<key>Variable</key>
									<string>Local_Alert_subtitle</string>
									<key>VariableConditionType</key>
									<string>IsNotEmpty</string>
									<key>VariableValue</key>
									<string>value</string>
								</dict>
							</array>
							<key>ConditionListMatch</key>
							<string>All</string>
						</dict>
						<key>ElseActionListDisclosed</key>
						<false/>
						<key>ElseActions</key>
						<array/>
						<key>MacroActionType</key>
						<string>IfThenElse</string>
						<key>ThenActions</key>
						<array>
							<dict>
								<key>ActionUID</key>
								<integer>3518</integer>
								<key>MacroActionType</key>
								<string>SetVariableToText</string>
								<key>Text</key>
								<string>\L%Local_Alert_subtitle%\E</string>
								<key>Variable</key>
								<string>Local_Alert_subtitle</string>
							</dict>
						</array>
						<key>TimeOutAbortsMacro</key>
						<true/>
					</dict>
					<dict>
						<key>ActionUID</key>
						<integer>3519</integer>
						<key>Conditions</key>
						<dict>
							<key>ConditionList</key>
							<array>
								<dict>
									<key>ConditionType</key>
									<string>Variable</string>
									<key>Variable</key>
									<string>Local_Alert_message</string>
									<key>VariableConditionType</key>
									<string>IsNotEmpty</string>
									<key>VariableValue</key>
									<string>value</string>
								</dict>
							</array>
							<key>ConditionListMatch</key>
							<string>All</string>
						</dict>
						<key>ElseActionListDisclosed</key>
						<false/>
						<key>ElseActions</key>
						<array/>
						<key>MacroActionType</key>
						<string>IfThenElse</string>
						<key>ThenActions</key>
						<array>
							<dict>
								<key>ActionUID</key>
								<integer>3520</integer>
								<key>MacroActionType</key>
								<string>SetVariableToText</string>
								<key>Text</key>
								<string>\L%Local_Alert_message%\E</string>
								<key>Variable</key>
								<string>Local_Alert_message</string>
							</dict>
						</array>
						<key>TimeOutAbortsMacro</key>
						<true/>
					</dict>
					<dict>
						<key>ActionUID</key>
						<integer>3521</integer>
						<key>Conditions</key>
						<dict>
							<key>ConditionList</key>
							<array>
								<dict>
									<key>ConditionType</key>
									<string>Variable</string>
									<key>Variable</key>
									<string>Local_Alert_sound</string>
									<key>VariableConditionType</key>
									<string>IsNotEmpty</string>
									<key>VariableValue</key>
									<string>value</string>
								</dict>
							</array>
							<key>ConditionListMatch</key>
							<string>All</string>
						</dict>
						<key>ElseActionListDisclosed</key>
						<false/>
						<key>ElseActions</key>
						<array/>
						<key>MacroActionType</key>
						<string>IfThenElse</string>
						<key>ThenActions</key>
						<array>
							<dict>
								<key>ActionUID</key>
								<integer>3522</integer>
								<key>MacroActionType</key>
								<string>SetVariableToText</string>
								<key>Text</key>
								<string>\L%Local_Alert_sound%\E</string>
								<key>Variable</key>
								<string>Local_Alert_sound</string>
							</dict>
						</array>
						<key>TimeOutAbortsMacro</key>
						<true/>
					</dict>
				</array>
				<key>IsDisclosed</key>
				<false/>
				<key>MacroActionType</key>
				<string>Group</string>
				<key>TimeOutAbortsMacro</key>
				<true/>
			</dict>
			<dict>
				<key>ActionUID</key>
				<integer>3523</integer>
				<key>MacroActionType</key>
				<string>Comment</string>
				<key>StyledText</key>
				<data>
							cnRmZAAAAAADAAAAAgAA
							AAcAAABUWFQucnRmAQAA
							AC5kAgAAKwAAAAEAAABc
							AgAAe1xydGYxXGFuc2lc
							YW5zaWNwZzEyNTJcY29j
							b2FydGYyNTEzClxjb2Nv
							YXRleHRzY2FsaW5nMFxj
							b2NvYXBsYXRmb3JtMHtc
							Zm9udHRibFxmMFxmc3dp
							c3NcZmNoYXJzZXQwIEhl
							bHZldGljYTt9CntcY29s
							b3J0Ymw7XHJlZDI1NVxn
							cmVlbjI1NVxibHVlMjU1
							O1xyZWQwXGdyZWVuMFxi
							bHVlMDt9CntcKlxleHBh
							bmRlZGNvbG9ydGJsOztc
							Y3NzcmdiXGMwXGMwXGMw
							XGM4NDcwNlxjbmFtZSBj
							b250cm9sVGV4dENvbG9y
							O30KXHBhcmRcdHg1NjBc
							dHgxMTIwXHR4MTY4MFx0
							eDIyNDBcdHgyODAwXHR4
							MzM2MFx0eDM5MjBcdHg0
							NDgwXHR4NTA0MFx0eDU2
							MDBcdHg2MTYwXHR4Njcy
							MFxwYXJkaXJuYXR1cmFs
							XHBhcnRpZ2h0ZW5mYWN0
							b3IwCgpcZjBcZnMyNiBc
							Y2YyIEl0IGlzIEFTU1VN
							RUQgdGhhdCB0aGUgcGFy
							YW1ldGVyIHBhc3NlZCBp
							cyBhIEpTT04gb2JqZWN0
							IHdpdGggdGhlIGZvbGxv
							d2luZ1wKPiBIYXMgQk9U
							SCBhIFwnOTN0eXBlXCc5
							NCBhbmQgXCc5M3NvdW5k
							XCc5NCBmaWVsZFwKPiBI
							YXMgYXQgbGVhc3Qgb25l
							IG9mIHRoZSBmb2xsb3dp
							bmcgZmllbGRzOiBcJzkz
							dGl0bGVcJzk0LCBcJzkz
							c3VidGl0bGVcJzk0LCBh
							bmQvb3IgXCc5M21lc3Nh
							Z2VcJzk0fQEAAAAjAAAA
							AQAAAAcAAABUWFQucnRm
							EAAAAH/AdV+2AQAAAAAA
							AAAAAAA=
							</data>
				<key>Title</key>
				<string>Validate arguments</string>
			</dict>
			<dict>
				<key>ActionUID</key>
				<integer>3524</integer>
				<key>Actions</key>
				<array>
					<dict>
						<key>ActionUID</key>
						<integer>3525</integer>
						<key>Conditions</key>
						<dict>
							<key>ConditionList</key>
							<array>
								<dict>
									<key>ConditionType</key>
									<string>Variable</string>
									<key>Variable</key>
									<string>Local_Alert_type</string>
									<key>VariableConditionType</key>
									<string>IsNotEmpty</string>
									<key>VariableValue</key>
									<string>value</string>
								</dict>
								<dict>
									<key>ConditionType</key>
									<string>Variable</string>
									<key>Variable</key>
									<string>Local_Alert_sound</string>
									<key>VariableConditionType</key>
									<string>IsNotEmpty</string>
									<key>VariableValue</key>
									<string>value</string>
								</dict>
							</array>
							<key>ConditionListMatch</key>
							<string>All</string>
						</dict>
						<key>IsDisclosed</key>
						<false/>
						<key>MacroActionType</key>
						<string>Assert</string>
					</dict>
					<dict>
						<key>ActionUID</key>
						<integer>3526</integer>
						<key>MacroActionType</key>
						<string>Comment</string>
						<key>StyledText</key>
						<data>
								cnRmZAAAAAAD
								AAAAAgAAAAcA
								AABUWFQucnRm
								AQAAAC7kAQAA
								KwAAAAEAAADc
								AQAAe1xydGYx
								XGFuc2lcYW5z
								aWNwZzEyNTJc
								Y29jb2FydGYy
								NTEzClxjb2Nv
								YXRleHRzY2Fs
								aW5nMFxjb2Nv
								YXBsYXRmb3Jt
								MHtcZm9udHRi
								bFxmMFxmc3dp
								c3NcZmNoYXJz
								ZXQwIEhlbHZl
								dGljYTt9Cntc
								Y29sb3J0Ymw7
								XHJlZDI1NVxn
								cmVlbjI1NVxi
								bHVlMjU1O1xy
								ZWQwXGdyZWVu
								MFxibHVlMDt9
								CntcKlxleHBh
								bmRlZGNvbG9y
								dGJsOztcY3Nz
								cmdiXGMwXGMw
								XGMwXGM4NDcw
								NlxjbmFtZSBj
								b250cm9sVGV4
								dENvbG9yO30K
								XHBhcmRcdHg1
								NjBcdHgxMTIw
								XHR4MTY4MFx0
								eDIyNDBcdHgy
								ODAwXHR4MzM2
								MFx0eDM5MjBc
								dHg0NDgwXHR4
								NTA0MFx0eDU2
								MDBcdHg2MTYw
								XHR4NjcyMFxw
								YXJkaXJuYXR1
								cmFsXHBhcnRp
								Z2h0ZW5mYWN0
								b3IwCgpcZjBc
								ZnMyNiBcY2Yy
								IFRoZSB2YWxp
								ZGl0eSBvZiB0
								aGUgdGl0bGUs
								IHN1YnRpdGxl
								LCBhbmQgbWVz
								c2FnZSBwYXJt
								ZXRlcnMgYXJl
								IGEgZnVuY3Rp
								b24gb2YgdGhl
								IG5vdGlmaWNh
								dGlvbiB0eXBl
								Ln0BAAAAIwAA
								AAEAAAAHAAAA
								VFhULnJ0ZhAA
								AAD6eHdftgEA
								AAAAAAAAAAAA
									</data>
						<key>Title</key>
						<string>Contextual Validation</string>
					</dict>
					<dict>
						<key>ActionUID</key>
						<integer>3527</integer>
						<key>CaseEntries</key>
						<array>
							<dict>
								<key>Actions</key>
								<array>
									<dict>
										<key>ActionUID</key>
										<integer>3528</integer>
										<key>MacroActionType</key>
										<string>Comment</string>
										<key>StyledText</key>
										<data>
								cnRmZAAAAAAD
								AAAAAgAAAAcA
								AABUWFQucnRm
								AQAAAC6wAQAA
								KwAAAAEAAACo
								AQAAe1xydGYx
								XGFuc2lcYW5z
								aWNwZzEyNTJc
								Y29jb2FydGYy
								NTEzClxjb2Nv
								YXRleHRzY2Fs
								aW5nMFxjb2Nv
								YXBsYXRmb3Jt
								MHtcZm9udHRi
								bFxmMFxmc3dp
								c3NcZmNoYXJz
								ZXQwIEhlbHZl
								dGljYTt9Cntc
								Y29sb3J0Ymw7
								XHJlZDI1NVxn
								cmVlbjI1NVxi
								bHVlMjU1O1xy
								ZWQwXGdyZWVu
								MFxibHVlMDt9
								CntcKlxleHBh
								bmRlZGNvbG9y
								dGJsOztcY3Nz
								cmdiXGMwXGMw
								XGMwXGM4NDcw
								NlxjbmFtZSBj
								b250cm9sVGV4
								dENvbG9yO30K
								XHBhcmRcdHg1
								NjBcdHgxMTIw
								XHR4MTY4MFx0
								eDIyNDBcdHgy
								ODAwXHR4MzM2
								MFx0eDM5MjBc
								dHg0NDgwXHR4
								NTA0MFx0eDU2
								MDBcdHg2MTYw
								XHR4NjcyMFxw
								YXJkaXJuYXR1
								cmFsXHBhcnRp
								Z2h0ZW5mYWN0
								b3IwCgpcZjBc
								ZnMyNiBcY2Yy
								IE5vdGlmaWNh
								dGlvbnMgdXNl
								OiB0aXRsZSwg
								c3VidGl0bGUs
								IGFuZCBtZXNz
								YWdlfQEAAAAj
								AAAAAQAAAAcA
								AABUWFQucnRm
								EAAAAHx7d1+2
								AQAAAAAAAAAA
								AAA=
													</data>
										<key>Title</key>
										<string>Notification validation</string>
									</dict>
									<dict>
										<key>ActionUID</key>
										<integer>3529</integer>
										<key>Conditions</key>
										<dict>
											<key>ConditionList</key>
											<array>
												<dict>
													<key>ConditionType</key>
													<string>Variable</string>
													<key>Variable</key>
													<string>Local_Alert_title</string>
													<key>VariableConditionType</key>
													<string>IsNotEmpty</string>
													<key>VariableValue</key>
													<string>value</string>
												</dict>
												<dict>
													<key>ConditionType</key>
													<string>Variable</string>
													<key>Variable</key>
													<string>Local_Alert_subtitle</string>
													<key>VariableConditionType</key>
													<string>IsNotEmpty</string>
													<key>VariableValue</key>
													<string>value</string>
												</dict>
												<dict>
													<key>ConditionType</key>
													<string>Variable</string>
													<key>Variable</key>
													<string>Local_Alert_message</string>
													<key>VariableConditionType</key>
													<string>IsNotEmpty</string>
													<key>VariableValue</key>
													<string>value</string>
												</dict>
											</array>
											<key>ConditionListMatch</key>
											<string>Any</string>
										</dict>
										<key>MacroActionType</key>
										<string>Assert</string>
									</dict>
								</array>
								<key>ConditionType</key>
								<string>Matches</string>
								<key>TestValue</key>
								<string>notification</string>
							</dict>
							<dict>
								<key>Actions</key>
								<array>
									<dict>
										<key>ActionUID</key>
										<integer>3530</integer>
										<key>Conditions</key>
										<dict>
											<key>ConditionList</key>
											<array>
												<dict>
													<key>ConditionType</key>
													<string>Variable</string>
													<key>Variable</key>
													<string>Local_Alert_subtitle</string>
													<key>VariableConditionType</key>
													<string>IsNotEmpty</string>
													<key>VariableValue</key>
													<string>value</string>
												</dict>
											</array>
											<key>ConditionListMatch</key>
											<string>Any</string>
										</dict>
										<key>MacroActionType</key>
										<string>Assert</string>
									</dict>
								</array>
								<key>ConditionType</key>
								<string>Matches</string>
								<key>TestValue</key>
								<string>large_text</string>
							</dict>
							<dict>
								<key>ActionListDisclosed</key>
								<false/>
								<key>Actions</key>
								<array>
									<dict>
										<key>ActionUID</key>
										<integer>3531</integer>
										<key>Conditions</key>
										<dict>
											<key>ConditionList</key>
											<array>
												<dict>
													<key>ConditionType</key>
													<string>Variable</string>
													<key>Variable</key>
													<string>Local_Alert_subtitle</string>
													<key>VariableConditionType</key>
													<string>IsNotEmpty</string>
													<key>VariableValue</key>
													<string>value</string>
												</dict>
												<dict>
													<key>ConditionType</key>
													<string>Variable</string>
													<key>Variable</key>
													<string>Local_Alert_message</string>
													<key>VariableConditionType</key>
													<string>IsNotEmpty</string>
													<key>VariableValue</key>
													<string>value</string>
												</dict>
											</array>
											<key>ConditionListMatch</key>
											<string>Any</string>
										</dict>
										<key>MacroActionType</key>
										<string>Assert</string>
									</dict>
								</array>
								<key>ConditionType</key>
								<string>Matches</string>
								<key>TestValue</key>
								<string>window</string>
							</dict>
							<dict>
								<key>ActionListDisclosed</key>
								<false/>
								<key>Actions</key>
								<array>
									<dict>
										<key>ActionUID</key>
										<integer>3532</integer>
										<key>Conditions</key>
										<dict>
											<key>ConditionList</key>
											<array>
												<dict>
													<key>ConditionType</key>
													<string>Variable</string>
													<key>Variable</key>
													<string>Local_Alert_title</string>
													<key>VariableConditionType</key>
													<string>IsNotEmpty</string>
													<key>VariableValue</key>
													<string>value</string>
												</dict>
												<dict>
													<key>ConditionType</key>
													<string>Variable</string>
													<key>Variable</key>
													<string>Local_Alert_message</string>
													<key>VariableConditionType</key>
													<string>IsNotEmpty</string>
													<key>VariableValue</key>
													<string>value</string>
												</dict>
											</array>
											<key>ConditionListMatch</key>
											<string>Any</string>
										</dict>
										<key>MacroActionType</key>
										<string>Assert</string>
									</dict>
								</array>
								<key>ConditionType</key>
								<string>Matches</string>
								<key>TestValue</key>
								<string>alert</string>
							</dict>
							<dict>
								<key>ActionListDisclosed</key>
								<false/>
								<key>Actions</key>
								<array>
									<dict>
										<key>ActionUID</key>
										<integer>3533</integer>
										<key>MacroActionType</key>
										<string>Comment</string>
										<key>StyledText</key>
										<data>
								cnRmZAAAAAAD
								AAAAAgAAAAcA
								AABUWFQucnRm
								AQAAAC68AQAA
								KwAAAAEAAAC0
								AQAAe1xydGYx
								XGFuc2lcYW5z
								aWNwZzEyNTJc
								Y29jb2FydGYy
								NTEzClxjb2Nv
								YXRleHRzY2Fs
								aW5nMFxjb2Nv
								YXBsYXRmb3Jt
								MHtcZm9udHRi
								bFxmMFxmc3dp
								c3NcZmNoYXJz
								ZXQwIEhlbHZl
								dGljYTt9Cntc
								Y29sb3J0Ymw7
								XHJlZDI1NVxn
								cmVlbjI1NVxi
								bHVlMjU1O1xy
								ZWQwXGdyZWVu
								MFxibHVlMDt9
								CntcKlxleHBh
								bmRlZGNvbG9y
								dGJsOztcY3Nz
								cmdiXGMwXGMw
								XGMwXGM4NDcw
								NlxjbmFtZSBj
								b250cm9sVGV4
								dENvbG9yO30K
								XHBhcmRcdHg1
								NjBcdHgxMTIw
								XHR4MTY4MFx0
								eDIyNDBcdHgy
								ODAwXHR4MzM2
								MFx0eDM5MjBc
								dHg0NDgwXHR4
								NTA0MFx0eDU2
								MDBcdHg2MTYw
								XHR4NjcyMFxw
								YXJkaXJuYXR1
								cmFsXHBhcnRp
								Z2h0ZW5mYWN0
								b3IwCgpcZjBc
								ZnMyNiBcY2Yy
								IFRoZXJlIGlz
								IG5vIHZpc3Vh
								bCBhbGVydCwg
								YnV0IGxlYXZl
								IHRoZSBzb3Vu
								ZCBhcyByZXF1
								ZXN0ZWQufQEA
								AAAjAAAAAQAA
								AAcAAABUWFQu
								cnRmEAAAAOvc
								d1+2AQAAAAAA
								AAAAAAA=
													</data>
										<key>Title</key>
										<string>Visual No-Op</string>
									</dict>
								</array>
								<key>ConditionType</key>
								<string>Matches</string>
								<key>TestValue</key>
								<string>audio_only</string>
							</dict>
							<dict>
								<key>ActionListDisclosed</key>
								<false/>
								<key>Actions</key>
								<array>
									<dict>
										<key>ActionUID</key>
										<integer>3534</integer>
										<key>MacroActionType</key>
										<string>Comment</string>
										<key>StyledText</key>
										<data>
								cnRmZAAAAAAD
								AAAAAgAAAAcA
								AABUWFQucnRm
								AQAAAC6pAQAA
								KwAAAAEAAACh
								AQAAe1xydGYx
								XGFuc2lcYW5z
								aWNwZzEyNTJc
								Y29jb2FydGYy
								NTEzClxjb2Nv
								YXRleHRzY2Fs
								aW5nMFxjb2Nv
								YXBsYXRmb3Jt
								MHtcZm9udHRi
								bFxmMFxmc3dp
								c3NcZmNoYXJz
								ZXQwIEhlbHZl
								dGljYTt9Cntc
								Y29sb3J0Ymw7
								XHJlZDI1NVxn
								cmVlbjI1NVxi
								bHVlMjU1O1xy
								ZWQwXGdyZWVu
								MFxibHVlMDt9
								CntcKlxleHBh
								bmRlZGNvbG9y
								dGJsOztcY3Nz
								cmdiXGMwXGMw
								XGMwXGM4NDcw
								NlxjbmFtZSBj
								b250cm9sVGV4
								dENvbG9yO30K
								XHBhcmRcdHg1
								NjBcdHgxMTIw
								XHR4MTY4MFx0
								eDIyNDBcdHgy
								ODAwXHR4MzM2
								MFx0eDM5MjBc
								dHg0NDgwXHR4
								NTA0MFx0eDU2
								MDBcdHg2MTYw
								XHR4NjcyMFxw
								YXJkaXJuYXR1
								cmFsXHBhcnRp
								Z2h0ZW5mYWN0
								b3IwCgpcZjBc
								ZnMyNiBcY2Yy
								IFNpbGVudCBu
								b3RpZmljYXRp
								b25zIGRvIG5v
								dCBkbyBhbnl0
								aGluZy59AQAA
								ACMAAAABAAAA
								BwAAAFRYVC5y
								dGYQAAAAGDp1
								X7YBAAAAAAAA
								AAAAAA==
													</data>
										<key>Title</key>
										<string>No-Op</string>
									</dict>
								</array>
								<key>ConditionType</key>
								<string>Matches</string>
								<key>TestValue</key>
								<string>silent</string>
							</dict>
							<dict>
								<key>ActionListDisclosed</key>
								<false/>
								<key>Actions</key>
								<array>
									<dict>
										<key>ActionUID</key>
										<integer>3535</integer>
										<key>MacroActionType</key>
										<string>Comment</string>
										<key>StyledText</key>
										<data>
								cnRmZAAAAAAD
								AAAAAgAAAAcA
								AABUWFQucnRm
								AQAAAC6GAAAA
								KwAAAAEAAAB+
								AAAAe1xydGYx
								XGFuc2lcYW5z
								aWNwZzEyNTJc
								Y29jb2FydGYx
								NTA0XGNvY29h
								c3VicnRmODMw
								CntcZm9udHRi
								bH0Ke1xjb2xv
								cnRibDtccmVk
								MjU1XGdyZWVu
								MjU1XGJsdWUy
								NTU7fQp7XCpc
								ZXhwYW5kZWRj
								b2xvcnRibDs7
								fQp9AQAAACMA
								AAABAAAABwAA
								AFRYVC5ydGYQ
								AAAAlmygWbYB
								AAAAAAAAAAAA
								AA==
													</data>
										<key>Title</key>
										<string>Unhandled type</string>
									</dict>
									<dict>
										<key>Action</key>
										<string>CancelThisMacro</string>
										<key>ActionUID</key>
										<integer>3536</integer>
										<key>MacroActionType</key>
										<string>Cancel</string>
									</dict>
								</array>
								<key>ConditionType</key>
								<string>Otherwise</string>
								<key>TestValue</key>
								<string></string>
							</dict>
						</array>
						<key>MacroActionType</key>
						<string>Switch</string>
						<key>Source</key>
						<string>Variable</string>
						<key>Variable</key>
						<string>Local_Alert_type</string>
					</dict>
				</array>
				<key>IsDisclosed</key>
				<false/>
				<key>MacroActionType</key>
				<string>Group</string>
				<key>TimeOutAbortsMacro</key>
				<true/>
			</dict>
			<dict>
				<key>ActionUID</key>
				<integer>3537</integer>
				<key>MacroActionType</key>
				<string>Comment</string>
				<key>StyledText</key>
				<data>
							cnRmZAAAAAADAAAAAgAA
							AAcAAABUWFQucnRmAQAA
							AC50AgAAKwAAAAEAAABs
							AgAAe1xydGYxXGFuc2lc
							YW5zaWNwZzEyNTJcY29j
							b2FydGYyNTEzClxjb2Nv
							YXRleHRzY2FsaW5nMFxj
							b2NvYXBsYXRmb3JtMHtc
							Zm9udHRibFxmMFxmc3dp
							c3NcZmNoYXJzZXQwIEhl
							bHZldGljYTt9CntcY29s
							b3J0Ymw7XHJlZDI1NVxn
							cmVlbjI1NVxibHVlMjU1
							O1xyZWQwXGdyZWVuMFxi
							bHVlMDt9CntcKlxleHBh
							bmRlZGNvbG9ydGJsOztc
							Y3NzcmdiXGMwXGMwXGMw
							XGM4NDcwNlxjbmFtZSBj
							b250cm9sVGV4dENvbG9y
							O30KXHBhcmRcdHg1NjBc
							dHgxMTIwXHR4MTY4MFx0
							eDIyNDBcdHgyODAwXHR4
							MzM2MFx0eDM5MjBcdHg0
							NDgwXHR4NTA0MFx0eDU2
							MDBcdHg2MTYwXHR4Njcy
							MFxwYXJkaXJuYXR1cmFs
							XHBhcnRpZ2h0ZW5mYWN0
							b3IwCgpcZjBcZnMyNiBc
							Y2YyIE1ha2UgdGhlIG5v
							dGlmaWNhdGlvbiBhY2Nv
							cmRpbmcgdG8gdGhlIHJl
							cXVlc3QuXApTdXBwb3J0
							ZWQgbm90aWZpY2F0aW9u
							czogTm90aWZpY2F0aW9u
							LCBMYXJnZV9UZXh0LCBX
							aW5kb3csIEFsZXJ0LCBh
							bmQgU2lsZW50XApOb3Rl
							czogU2lsZW50IGFsc28g
							dHVybnMgb2ZmIHRoZSBz
							b3VuZCBpZiBvbmUgaXMg
							c3BlY2lmaWVkLlwKICAg
							ICAgICAgICAgVW5zcGVj
							aWZpZWQgdHlwZXMgY2F1
							c2UgdGhlIG1hY3JvIHRv
							IGFib3J0Ln0BAAAAIwAA
							AAEAAAAHAAAAVFhULnJ0
							ZhAAAAAjSHVftgEAAAAA
							AAAAAAAA
							</data>
				<key>Title</key>
				<string>Notification</string>
			</dict>
			<dict>
				<key>ActionUID</key>
				<integer>3538</integer>
				<key>CaseEntries</key>
				<array>
					<dict>
						<key>ActionListDisclosed</key>
						<false/>
						<key>Actions</key>
						<array>
							<dict>
								<key>ActionUID</key>
								<integer>3539</integer>
								<key>MacroActionType</key>
								<string>Notification</string>
								<key>SoundName</key>
								<string></string>
								<key>Subtitle</key>
								<string>%Local_Alert_subtitle%</string>
								<key>Text</key>
								<string>%Local_Alert_message%</string>
								<key>Title</key>
								<string>%Local_Alert_title%</string>
							</dict>
						</array>
						<key>ConditionType</key>
						<string>Is</string>
						<key>TestValue</key>
						<string>notification</string>
					</dict>
					<dict>
						<key>ActionListDisclosed</key>
						<false/>
						<key>Actions</key>
						<array>
							<dict>
								<key>Action</key>
								<string>DisplayLarge</string>
								<key>ActionUID</key>
								<integer>3540</integer>
								<key>MacroActionType</key>
								<string>InsertText</string>
								<key>Text</key>
								<string>%Local_Alert_subtitle%</string>
							</dict>
						</array>
						<key>ConditionType</key>
						<string>Is</string>
						<key>TestValue</key>
						<string>large_text</string>
					</dict>
					<dict>
						<key>ActionListDisclosed</key>
						<false/>
						<key>Actions</key>
						<array>
							<dict>
								<key>Action</key>
								<string>DisplayWindow</string>
								<key>ActionUID</key>
								<integer>3541</integer>
								<key>MacroActionType</key>
								<string>InsertText</string>
								<key>StyledText</key>
								<data>
								cnRmZAAAAAAD
								AAAAAgAAAAcA
								AABUWFQucnRm
								AQAAAC7CAQAA
								KwAAAAEAAAC6
								AQAAe1xydGYx
								XGFuc2lcYW5z
								aWNwZzEyNTJc
								Y29jb2FydGYy
								NTEzClxjb2Nv
								YXRleHRzY2Fs
								aW5nMFxjb2Nv
								YXBsYXRmb3Jt
								MHtcZm9udHRi
								bFxmMFxmc3dp
								c3NcZmNoYXJz
								ZXQwIEhlbHZl
								dGljYTt9Cntc
								Y29sb3J0Ymw7
								XHJlZDI1NVxn
								cmVlbjI1NVxi
								bHVlMjU1O1xy
								ZWQwXGdyZWVu
								MFxibHVlMDt9
								CntcKlxleHBh
								bmRlZGNvbG9y
								dGJsOztcY3Nz
								cmdiXGMwXGMw
								XGMwXGM4NDcw
								NlxjbmFtZSBj
								b250cm9sVGV4
								dENvbG9yO30K
								XHBhcmRcdHg1
								NjBcdHgxMTIw
								XHR4MTY4MFx0
								eDIyNDBcdHgy
								ODAwXHR4MzM2
								MFx0eDM5MjBc
								dHg0NDgwXHR4
								NTA0MFx0eDU2
								MDBcdHg2MTYw
								XHR4NjcyMFxw
								YXJkaXJuYXR1
								cmFsXHBhcnRp
								Z2h0ZW5mYWN0
								b3IwCgpcZjBc
								ZnMyNiBcY2Yy
								IFN1Yi1UaXRs
								ZTogJUxvY2Fs
								X0FsZXJ0X3N1
								YnRpdGxlJVwK
								TWVzc2FnZTog
								JUxvY2FsX0Fs
								ZXJ0X21lc3Nh
								Z2UlfQEAAAAj
								AAAAAQAAAAcA
								AABUWFQucnRm
								EAAAAMDad1+2
								AQAAAAAAAAAA
								AAA=
											</data>
								<key>Text</key>
								<string>Sub-Title: %Local_Alert_subtitle%
Message: %Local_Alert_message%</string>
							</dict>
						</array>
						<key>ConditionType</key>
						<string>Is</string>
						<key>TestValue</key>
						<string>window</string>
					</dict>
					<dict>
						<key>ActionListDisclosed</key>
						<false/>
						<key>Actions</key>
						<array>
							<dict>
								<key>ActionUID</key>
								<integer>3542</integer>
								<key>MacroActionType</key>
								<string>Alert</string>
								<key>SoundPath</key>
								<string></string>
								<key>Text</key>
								<string>%Local_Alert_message%</string>
								<key>TimeOutAbortsMacro</key>
								<true/>
								<key>Title</key>
								<string>%Local_Alert_title%</string>
							</dict>
						</array>
						<key>ConditionType</key>
						<string>Is</string>
						<key>TestValue</key>
						<string>alert</string>
					</dict>
					<dict>
						<key>ActionListDisclosed</key>
						<false/>
						<key>Actions</key>
						<array>
							<dict>
								<key>ActionUID</key>
								<integer>3543</integer>
								<key>MacroActionType</key>
								<string>Comment</string>
								<key>StyledText</key>
								<data>
								cnRmZAAAAAAD
								AAAAAgAAAAcA
								AABUWFQucnRm
								AQAAAC7MAQAA
								KwAAAAEAAADE
								AQAAe1xydGYx
								XGFuc2lcYW5z
								aWNwZzEyNTJc
								Y29jb2FydGYy
								NTEzClxjb2Nv
								YXRleHRzY2Fs
								aW5nMFxjb2Nv
								YXBsYXRmb3Jt
								MHtcZm9udHRi
								bFxmMFxmc3dp
								c3NcZmNoYXJz
								ZXQwIEhlbHZl
								dGljYTt9Cntc
								Y29sb3J0Ymw7
								XHJlZDI1NVxn
								cmVlbjI1NVxi
								bHVlMjU1O1xy
								ZWQwXGdyZWVu
								MFxibHVlMDt9
								CntcKlxleHBh
								bmRlZGNvbG9y
								dGJsOztcY3Nz
								cmdiXGMwXGMw
								XGMwXGM4NDcw
								NlxjbmFtZSBj
								b250cm9sVGV4
								dENvbG9yO30K
								XHBhcmRcdHg1
								NjBcdHgxMTIw
								XHR4MTY4MFx0
								eDIyNDBcdHgy
								ODAwXHR4MzM2
								MFx0eDM5MjBc
								dHg0NDgwXHR4
								NTA0MFx0eDU2
								MDBcdHg2MTYw
								XHR4NjcyMFxw
								YXJkaXJuYXR1
								cmFsXHBhcnRp
								Z2h0ZW5mYWN0
								b3IwCgpcZjBc
								ZnMyNiBcY2Yy
								IFNpbGVudCBu
								b3RpZmljYXRp
								b25zIGRvIG5v
								dCBkbyBhbnl0
								aGluZy5cCkVu
								c3VyZSB0aGVy
								ZSBpcyBubyBz
								b3VuZCBhcyB3
								ZWxsLn0BAAAA
								IwAAAAEAAAAH
								AAAAVFhULnJ0
								ZhAAAABKR3Vf
								tgEAAAAAAAAA
								AAAA
											</data>
								<key>Title</key>
								<string>No-Op</string>
							</dict>
							<dict>
								<key>ActionUID</key>
								<integer>3544</integer>
								<key>MacroActionType</key>
								<string>SetVariableToText</string>
								<key>Text</key>
								<string>none</string>
								<key>Variable</key>
								<string>Local_Alert_sound</string>
							</dict>
						</array>
						<key>ConditionType</key>
						<string>Is</string>
						<key>TestValue</key>
						<string>silent</string>
					</dict>
					<dict>
						<key>ActionListDisclosed</key>
						<false/>
						<key>Actions</key>
						<array/>
						<key>ConditionType</key>
						<string>Is</string>
						<key>TestValue</key>
						<string>audio_only</string>
					</dict>
					<dict>
						<key>ActionListDisclosed</key>
						<false/>
						<key>Actions</key>
						<array>
							<dict>
								<key>ActionUID</key>
								<integer>3545</integer>
								<key>MacroActionType</key>
								<string>Comment</string>
								<key>StyledText</key>
								<data>
								cnRmZAAAAAAD
								AAAAAgAAAAcA
								AABUWFQucnRm
								AQAAAC6mAQAA
								KwAAAAEAAACe
								AQAAe1xydGYx
								XGFuc2lcYW5z
								aWNwZzEyNTJc
								Y29jb2FydGYy
								NTEzClxjb2Nv
								YXRleHRzY2Fs
								aW5nMFxjb2Nv
								YXBsYXRmb3Jt
								MHtcZm9udHRi
								bFxmMFxmc3dp
								c3NcZmNoYXJz
								ZXQwIEhlbHZl
								dGljYTt9Cntc
								Y29sb3J0Ymw7
								XHJlZDI1NVxn
								cmVlbjI1NVxi
								bHVlMjU1O1xy
								ZWQwXGdyZWVu
								MFxibHVlMDt9
								CntcKlxleHBh
								bmRlZGNvbG9y
								dGJsOztcY3Nz
								cmdiXGMwXGMw
								XGMwXGM4NDcw
								NlxjbmFtZSBj
								b250cm9sVGV4
								dENvbG9yO30K
								XHBhcmRcdHg1
								NjBcdHgxMTIw
								XHR4MTY4MFx0
								eDIyNDBcdHgy
								ODAwXHR4MzM2
								MFx0eDM5MjBc
								dHg0NDgwXHR4
								NTA0MFx0eDU2
								MDBcdHg2MTYw
								XHR4NjcyMFxw
								YXJkaXJuYXR1
								cmFsXHBhcnRp
								Z2h0ZW5mYWN0
								b3IwCgpcZjBc
								ZnMyNiBcY2Yy
								IE5vdCBwb3Nz
								aWJsZSBkdWUg
								dG8gdmFsaWRh
								dGlvbiBhYm92
								ZS59AQAAACMA
								AAABAAAABwAA
								AFRYVC5ydGYQ
								AAAAhNt3X7YB
								AAAAAAAAAAAA
								AA==
											</data>
								<key>Title</key>
								<string>Unhandled case</string>
							</dict>
							<dict>
								<key>Action</key>
								<string>CancelThisMacro</string>
								<key>ActionUID</key>
								<integer>3546</integer>
								<key>MacroActionType</key>
								<string>Cancel</string>
							</dict>
						</array>
						<key>ConditionType</key>
						<string>Otherwise</string>
						<key>TestValue</key>
						<string></string>
					</dict>
				</array>
				<key>IsDisclosed</key>
				<false/>
				<key>MacroActionType</key>
				<string>Switch</string>
				<key>Source</key>
				<string>Variable</string>
				<key>Variable</key>
				<string>Local_Alert_type</string>
			</dict>
			<dict>
				<key>ActionUID</key>
				<integer>3547</integer>
				<key>MacroActionType</key>
				<string>Comment</string>
				<key>StyledText</key>
				<data>
							cnRmZAAAAAADAAAAAgAA
							AAcAAABUWFQucnRmAQAA
							AC59AgAAKwAAAAEAAAB1
							AgAAe1xydGYxXGFuc2lc
							YW5zaWNwZzEyNTJcY29j
							b2FydGYyNTEzClxjb2Nv
							YXRleHRzY2FsaW5nMFxj
							b2NvYXBsYXRmb3JtMHtc
							Zm9udHRibFxmMFxmc3dp
							c3NcZmNoYXJzZXQwIEhl
							bHZldGljYTt9CntcY29s
							b3J0Ymw7XHJlZDI1NVxn
							cmVlbjI1NVxibHVlMjU1
							O1xyZWQwXGdyZWVuMFxi
							bHVlMDt9CntcKlxleHBh
							bmRlZGNvbG9ydGJsOztc
							Y3NzcmdiXGMwXGMwXGMw
							XGM4NDcwNlxjbmFtZSBj
							b250cm9sVGV4dENvbG9y
							O30KXHBhcmRcdHg1NjBc
							dHgxMTIwXHR4MTY4MFx0
							eDIyNDBcdHgyODAwXHR4
							MzM2MFx0eDM5MjBcdHg0
							NDgwXHR4NTA0MFx0eDU2
							MDBcdHg2MTYwXHR4Njcy
							MFxwYXJkaXJuYXR1cmFs
							XHBhcnRpZ2h0ZW5mYWN0
							b3IwCgpcZjBcZnMyNiBc
							Y2YyIE1ha2UgdGhlIHNv
							dW5kIGFjY29yZGluZyB0
							byB0aGUgcmVxdWVzdC5c
							ClN1cHBvcnRlZCBzb3Vu
							ZHM6IE5vbmUsIEJhc3Nv
							LCBCbG93LCBCb3R0bGUs
							IEZyb2csIEZ1bmssIEds
							YXNzLCBIZXJvLCBNb3Jz
							ZSwgUGluZywgUG9wLCBQ
							dXJyLCBTb3N1bWksIFN1
							Ym1hcmluZSwgYW5kIFN5
							c3RlbV9CZWVwXApUaGUg
							c291bmRzIGlzIHNlbnQg
							dHAgdGhlIFwnOTFTb3Vu
							ZCBFZmZlY3RzIE91dHB1
							dCBEZXZpY2VcJzkyIGF0
							IG1heGltdW0gdm9sdW1l
							Ln0BAAAAIwAAAAEAAAAH
							AAAAVFhULnJ0ZhAAAAAk
							R3VftgEAAAAAAAAAAAAA
							</data>
				<key>Title</key>
				<string>Sound</string>
			</dict>
			<dict>
				<key>ActionUID</key>
				<integer>3548</integer>
				<key>CaseEntries</key>
				<array>
					<dict>
						<key>Actions</key>
						<array>
							<dict>
								<key>ActionUID</key>
								<integer>3549</integer>
								<key>DeviceID</key>
								<string>SOUNDEFFECTS</string>
								<key>MacroActionType</key>
								<string>PlaySound</string>
								<key>Path</key>
								<string>/System/Library/Sounds/Basso.aiff</string>
								<key>TimeOutAbortsMacro</key>
								<true/>
							</dict>
						</array>
						<key>ConditionType</key>
						<string>Is</string>
						<key>TestValue</key>
						<string>basso</string>
					</dict>
					<dict>
						<key>Actions</key>
						<array>
							<dict>
								<key>ActionUID</key>
								<integer>3550</integer>
								<key>DeviceID</key>
								<string>SOUNDEFFECTS</string>
								<key>MacroActionType</key>
								<string>PlaySound</string>
								<key>Path</key>
								<string>/System/Library/Sounds/Blow.aiff</string>
								<key>TimeOutAbortsMacro</key>
								<true/>
							</dict>
						</array>
						<key>ConditionType</key>
						<string>Is</string>
						<key>TestValue</key>
						<string>blow</string>
					</dict>
					<dict>
						<key>Actions</key>
						<array>
							<dict>
								<key>ActionUID</key>
								<integer>3551</integer>
								<key>DeviceID</key>
								<string>SOUNDEFFECTS</string>
								<key>MacroActionType</key>
								<string>PlaySound</string>
								<key>Path</key>
								<string>/System/Library/Sounds/Bottle.aiff</string>
								<key>TimeOutAbortsMacro</key>
								<true/>
							</dict>
						</array>
						<key>ConditionType</key>
						<string>Is</string>
						<key>TestValue</key>
						<string>bottle</string>
					</dict>
					<dict>
						<key>Actions</key>
						<array>
							<dict>
								<key>ActionUID</key>
								<integer>3552</integer>
								<key>DeviceID</key>
								<string>SOUNDEFFECTS</string>
								<key>MacroActionType</key>
								<string>PlaySound</string>
								<key>Path</key>
								<string>/System/Library/Sounds/Frog.aiff</string>
								<key>TimeOutAbortsMacro</key>
								<true/>
							</dict>
						</array>
						<key>ConditionType</key>
						<string>Is</string>
						<key>TestValue</key>
						<string>frog</string>
					</dict>
					<dict>
						<key>Actions</key>
						<array>
							<dict>
								<key>ActionUID</key>
								<integer>3553</integer>
								<key>DeviceID</key>
								<string>SOUNDEFFECTS</string>
								<key>MacroActionType</key>
								<string>PlaySound</string>
								<key>Path</key>
								<string>/System/Library/Sounds/Funk.aiff</string>
								<key>TimeOutAbortsMacro</key>
								<true/>
							</dict>
						</array>
						<key>ConditionType</key>
						<string>Is</string>
						<key>TestValue</key>
						<string>funk</string>
					</dict>
					<dict>
						<key>Actions</key>
						<array>
							<dict>
								<key>ActionUID</key>
								<integer>3554</integer>
								<key>DeviceID</key>
								<string>SOUNDEFFECTS</string>
								<key>MacroActionType</key>
								<string>PlaySound</string>
								<key>Path</key>
								<string>/System/Library/Sounds/Glass.aiff</string>
								<key>TimeOutAbortsMacro</key>
								<true/>
							</dict>
						</array>
						<key>ConditionType</key>
						<string>Is</string>
						<key>TestValue</key>
						<string>glass</string>
					</dict>
					<dict>
						<key>Actions</key>
						<array>
							<dict>
								<key>ActionUID</key>
								<integer>3555</integer>
								<key>DeviceID</key>
								<string>SOUNDEFFECTS</string>
								<key>MacroActionType</key>
								<string>PlaySound</string>
								<key>Path</key>
								<string>/System/Library/Sounds/Hero.aiff</string>
								<key>TimeOutAbortsMacro</key>
								<true/>
							</dict>
						</array>
						<key>ConditionType</key>
						<string>Is</string>
						<key>TestValue</key>
						<string>hero</string>
					</dict>
					<dict>
						<key>Actions</key>
						<array>
							<dict>
								<key>ActionUID</key>
								<integer>3556</integer>
								<key>DeviceID</key>
								<string>SOUNDEFFECTS</string>
								<key>MacroActionType</key>
								<string>PlaySound</string>
								<key>Path</key>
								<string>/System/Library/Sounds/Morse.aiff</string>
								<key>TimeOutAbortsMacro</key>
								<true/>
							</dict>
						</array>
						<key>ConditionType</key>
						<string>Is</string>
						<key>TestValue</key>
						<string>morse</string>
					</dict>
					<dict>
						<key>Actions</key>
						<array>
							<dict>
								<key>ActionUID</key>
								<integer>3557</integer>
								<key>DeviceID</key>
								<string>SOUNDEFFECTS</string>
								<key>MacroActionType</key>
								<string>PlaySound</string>
								<key>Path</key>
								<string>/System/Library/Sounds/Ping.aiff</string>
								<key>TimeOutAbortsMacro</key>
								<true/>
							</dict>
						</array>
						<key>ConditionType</key>
						<string>Is</string>
						<key>TestValue</key>
						<string>ping</string>
					</dict>
					<dict>
						<key>Actions</key>
						<array>
							<dict>
								<key>ActionUID</key>
								<integer>3558</integer>
								<key>DeviceID</key>
								<string>SOUNDEFFECTS</string>
								<key>MacroActionType</key>
								<string>PlaySound</string>
								<key>Path</key>
								<string>/System/Library/Sounds/Pop.aiff</string>
								<key>TimeOutAbortsMacro</key>
								<true/>
							</dict>
						</array>
						<key>ConditionType</key>
						<string>Is</string>
						<key>TestValue</key>
						<string>pop</string>
					</dict>
					<dict>
						<key>Actions</key>
						<array>
							<dict>
								<key>ActionUID</key>
								<integer>3559</integer>
								<key>DeviceID</key>
								<string>SOUNDEFFECTS</string>
								<key>MacroActionType</key>
								<string>PlaySound</string>
								<key>Path</key>
								<string>/System/Library/Sounds/Purr.aiff</string>
								<key>TimeOutAbortsMacro</key>
								<true/>
							</dict>
						</array>
						<key>ConditionType</key>
						<string>Is</string>
						<key>TestValue</key>
						<string>purr</string>
					</dict>
					<dict>
						<key>Actions</key>
						<array>
							<dict>
								<key>ActionUID</key>
								<integer>3560</integer>
								<key>DeviceID</key>
								<string>SOUNDEFFECTS</string>
								<key>MacroActionType</key>
								<string>PlaySound</string>
								<key>Path</key>
								<string>/System/Library/Sounds/Sosumi.aiff</string>
								<key>TimeOutAbortsMacro</key>
								<true/>
							</dict>
						</array>
						<key>ConditionType</key>
						<string>Is</string>
						<key>TestValue</key>
						<string>sosumi</string>
					</dict>
					<dict>
						<key>Actions</key>
						<array>
							<dict>
								<key>ActionUID</key>
								<integer>3561</integer>
								<key>DeviceID</key>
								<string>SOUNDEFFECTS</string>
								<key>MacroActionType</key>
								<string>PlaySound</string>
								<key>Path</key>
								<string>/System/Library/Sounds/Submarine.aiff</string>
								<key>TimeOutAbortsMacro</key>
								<true/>
							</dict>
						</array>
						<key>ConditionType</key>
						<string>Is</string>
						<key>TestValue</key>
						<string>submarine</string>
					</dict>
					<dict>
						<key>Actions</key>
						<array>
							<dict>
								<key>ActionUID</key>
								<integer>3562</integer>
								<key>DeviceID</key>
								<string>SOUNDEFFECTS</string>
								<key>MacroActionType</key>
								<string>PlaySound</string>
								<key>Path</key>
								<string>/</string>
								<key>TimeOutAbortsMacro</key>
								<true/>
							</dict>
						</array>
						<key>ConditionType</key>
						<string>Is</string>
						<key>TestValue</key>
						<string>system_beep</string>
					</dict>
					<dict>
						<key>Actions</key>
						<array>
							<dict>
								<key>ActionUID</key>
								<integer>3563</integer>
								<key>DeviceID</key>
								<string>SOUNDEFFECTS</string>
								<key>MacroActionType</key>
								<string>PlaySound</string>
								<key>Path</key>
								<string>/System/Library/Sounds/Tink.aiff</string>
								<key>TimeOutAbortsMacro</key>
								<true/>
							</dict>
						</array>
						<key>ConditionType</key>
						<string>Is</string>
						<key>TestValue</key>
						<string>tink</string>
					</dict>
					<dict>
						<key>Actions</key>
						<array>
							<dict>
								<key>ActionUID</key>
								<integer>3564</integer>
								<key>MacroActionType</key>
								<string>Comment</string>
								<key>StyledText</key>
								<data>
								cnRmZAAAAAAD
								AAAAAgAAAAcA
								AABUWFQucnRm
								AQAAAC6OAQAA
								KwAAAAEAAACG
								AQAAe1xydGYx
								XGFuc2lcYW5z
								aWNwZzEyNTJc
								Y29jb2FydGYy
								NTEzClxjb2Nv
								YXRleHRzY2Fs
								aW5nMFxjb2Nv
								YXBsYXRmb3Jt
								MHtcZm9udHRi
								bFxmMFxmc3dp
								c3NcZmNoYXJz
								ZXQwIEhlbHZl
								dGljYTt9Cntc
								Y29sb3J0Ymw7
								XHJlZDI1NVxn
								cmVlbjI1NVxi
								bHVlMjU1O1xy
								ZWQwXGdyZWVu
								MFxibHVlMDt9
								CntcKlxleHBh
								bmRlZGNvbG9y
								dGJsOztcY3Nz
								cmdiXGMwXGMw
								XGMwXGM4NDcw
								NlxjbmFtZSBj
								b250cm9sVGV4
								dENvbG9yO30K
								XHBhcmRcdHg1
								NjBcdHgxMTIw
								XHR4MTY4MFx0
								eDIyNDBcdHgy
								ODAwXHR4MzM2
								MFx0eDM5MjBc
								dHg0NDgwXHR4
								NTA0MFx0eDU2
								MDBcdHg2MTYw
								XHR4NjcyMFxw
								YXJkaXJuYXR1
								cmFsXHBhcnRp
								Z2h0ZW5mYWN0
								b3IwCgpcZjBc
								ZnMyNiBcY2Yy
								IE1ha2Ugbm8g
								c291bmR9AQAA
								ACMAAAABAAAA
								BwAAAFRYVC5y
								dGYQAAAA0UV1
								X7YBAAAAAAAA
								AAAAAA==
											</data>
								<key>Title</key>
								<string>None</string>
							</dict>
						</array>
						<key>ConditionType</key>
						<string>Otherwise</string>
						<key>TestValue</key>
						<string></string>
					</dict>
				</array>
				<key>MacroActionType</key>
				<string>Switch</string>
				<key>Source</key>
				<string>Variable</string>
				<key>Variable</key>
				<string>Local_Alert_sound</string>
			</dict>
		</array>
		<key>CreationDate</key>
		<real>623207537.909217</real>
		<key>ModificationDate</key>
		<real>669328709.24960697</real>
		<key>Name</key>
		<string>DoNotification (Grumpy)</string>
		<key>Triggers</key>
		<array/>
		<key>UID</key>
		<string>379F6603-4069-41CE-A542-BA7FCD6B3F49</string>
	</dict>
</array>
</plist>
